nsg/__init__.py
nsg/common/__init__.py
nsg/common/bounding_box.py
nsg/common/coordinate.py
nsg/common/enum_with_attributes.py
nsg/common/spatial_reference_system.py
nsg/tile_cache/__init__.py
nsg/tile_cache/tile.py
nsg/tile_cache/tile_cache.py
nsg/tile_cache/tile_origin.py
nsg/tile_cache/tile_scheme.py
nsglib-3.0.0.0.dist-info/LICENSE.txt
nsglib-3.0.0.0.dist-info/METADATA
nsglib-3.0.0.0.dist-info/WHEEL
nsglib-3.0.0.0.dist-info/top_level.txt
nsglib-3.0.0.0.dist-info/RECORD
