Metadata-Version: 2.1
Name: nsglib
Version: 3.0.0.0
Summary: NSG Common Python Library
Home-page: https://gitlab.com/GitLabRGI/nsg/nsg-tile-cache/nsg-common-library
Author: Richard Kim & Jenifer Cochran
Author-email: developer.publishers@rgi-corp.com
License: MIT
Platform: UNKNOWN
Classifier: Programming Language :: Python :: 3.7
Classifier: License :: OSI Approved :: MIT License
Classifier: Operating System :: OS Independent
Classifier: Natural Language :: English
Requires-Python: >3.7.0
